parser_ci_AP/__init__.py
parser_ci_AP/define_info.py
parser_ci_AP/errors_info.py
parser_ci_AP/function_info.py
parser_ci_AP/logger.py
parser_ci_AP/project.py
parser_ci_AP/project_file.py
parser_ci_AP/type_info.py
parser_ci_AP/variable_info.py
parser_ci_ap-0.1.40.dist-info/licenses/LICENSE
parser_ci_ap-0.1.40.dist-info/METADATA
parser_ci_ap-0.1.40.dist-info/WHEEL
parser_ci_ap-0.1.40.dist-info/top_level.txt
parser_ci_ap-0.1.40.dist-info/RECORD
