Metadata-Version: 2.4
Name: parser-ci-AP
Version: 0.1.40
Summary: C code parser based on Clang
Home-page: https://github.com/yourusername/parser-ci
Author: Александр
Author-email: sanyapetrooo@gmail.com
License: MIT
Classifier: Programming Language :: Python :: 3
Classifier: License :: OSI Approved :: MIT License
Classifier: Operating System :: OS Independent
Requires-Python: >=3.13
License-File: LICENSE
Requires-Dist: chardet==5.2.0
Requires-Dist: libclang==18.1.1
Dynamic: author
Dynamic: author-email
Dynamic: classifier
Dynamic: description
Dynamic: description-content-type
Dynamic: home-page
Dynamic: license
Dynamic: license-file
Dynamic: requires-dist
Dynamic: requires-python
Dynamic: summary
